[1,["fflNpWVzVBB5MwasPy4Tqd@f9941","fdoJXLgx1GAa2UhGATlj3o","e1e0UmV6JI06zJzwnzCqE4","94TsI0WiNNCJfOxekMd8gL@f9941","94TsI0WiNNCJfOxekMd8gL@6c48a","17XX0IAuBFwK0v/Cgd0IWQ","fflNpWVzVBB5MwasPy4Tqd@6c48a"],["node","_spriteFrame","_textureSource","_customMaterial","_file","root","data"],[["cc.Node",["_name","_layer","_active","_components","_prefab","_parent","_children","_lpos"],0,9,4,1,2,5],"cc.SpriteFrame",["cc.UITransform",["node","__prefab","_contentSize"],3,1,4,5],["cc.ParticleSystem2D",["_name","duration","emissionRate","life","lifeVar","angle","angleVar","startSize","startSizeVar","speed","tangentialAccel","autoRemoveOnFinish","_custom","_totalParticles","speedVar","node","__prefab","posVar","gravity","_endColor","_customMaterial","_file","_spriteFrame"],-12,1,4,5,5,5,6,6,6],["cc.Prefab",["_name"],2],["cc.CompPrefabInfo",["fileId"],2],["cc.Animation",["node","__prefab","_clips"],3,1,4,3],["cc.PrefabInfo",["fileId","instance","targetOverrides","nestedPrefabInstanceRoots","root","asset"],-1,1,1],["cc.Sprite",["_sizeMode","_isTrimmedMode","node","__prefab","_color","_spriteFrame"],1,1,4,5,6]],[[5,0,2],[7,0,1,2,3,4,5,5],[2,0,1,1],[0,0,1,5,3,4,3],[0,0,2,1,5,3,4,7,4],[2,0,1,2,1],[8,0,1,2,3,4,5,3],[4,0,2],[0,0,1,6,3,4,3],[0,0,1,5,6,3,4,3],[6,0,1,2,1],[3,0,1,2,3,4,5,6,7,8,9,10,11,12,13,15,16,17,18,19,20,21,22,15],[3,0,1,2,3,4,5,6,7,8,9,14,10,11,12,13,15,16,17,18,19,20,21,22,16]],[[[{"name":"light2","rect":{"x":0,"y":0,"width":21,"height":21},"offset":{"x":0,"y":0},"originalSize":{"width":21,"height":21},"rotated":false,"capInsets":[0,0,0,0],"vertices":{"rawPosition":[-10.5,-10.5,0,10.5,-10.5,0,-10.5,10.5,0,10.5,10.5,0],"indexes":[0,1,2,2,1,3],"uv":[0,21,21,21,0,0,21,0],"nuv":[0,0,1,0,0,1,1,1],"minPos":{"x":-10.5,"y":-10.5,"z":0},"maxPos":{"x":10.5,"y":10.5,"z":0}},"packable":true,"pixelsToUnit":100,"pivot":{"x":0.5,"y":0.5},"meshType":0}],[1],0,[0],[2],[4]],[[[7,"Combo"],[8,"Combo",33554432,[-4],[[2,-2,[0,"99isCzzTNMFKjRFjg+9pVS"]],[10,-3,[0,"acLZdTDLpMybMW8P2yFGLx"],[8]]],[1,"573JybnklDNrWNC8YGk8La",null,null,null,-1,0]],[9,"node_combo",33554432,1,[-6,-7,-8,-9],[[2,-5,[0,"b0pR4VPj5N56mp3MpPQ8UF"]]],[1,"deJBYuqw1LDoj2sVk0Xc92",null,null,null,1,0]],[3,"combo_1",33554432,2,[[5,-10,[0,"80oO2dUElHyLYMcZ5PffRf"],[5,309,74]],[6,2,false,-11,[0,"cct3ZVEThMiJP22QYRng8x"],[4,16777215],0]],[1,"86/aw6g19DYrcqLBnIvg/Z",null,null,null,1,0]],[3,"combo",33554432,2,[[5,-12,[0,"b4jx/KJU9CoKIzO1yvCwQa"],[5,309,74]],[6,2,false,-13,[0,"5ai2uiOEpLo59Dw77wj5kG"],[4,16777215],1]],[1,"c3mBDR5G1Gzriv0JtAbnwP",null,null,null,1,0]],[4,"star",false,33554432,2,[[2,-14,[0,"4bdNl3ohRNs7nAAlyHr5Ju"]],[11,"Node<ParticleSystem2D>",0.2,200,0.6,0.5,180,0,30,15,50,0,true,true,15,-15,[0,"a1FgWUznVDQ63MYKau7Cz8"],[0,60,40],[0,15,0.8600000143051147],[4,4294967295],2,3,4]],[1,"36rXhURqpISroaHat0ZT49",null,null,null,1,0],[1,-155,-10,0]],[4,"star_one",false,33554432,2,[[2,-16,[0,"edXFqW/PpA0bNa8pfFz7ME"]],[12,"Node<ParticleSystem2D>",0.2,200,0.6,0.5,-180,0,30,15,-50,0,0,true,true,15,-17,[0,"0fi0n+MlNBt7Hl9k1RBa52"],[0,60,40],[0,15,0.8600000143051147],[4,4294967295],5,6,7]],[1,"ccQG6gKVlKLZ5+nhMCPf4O",null,null,null,1,0],[1,160,-10,0]]],0,[0,5,1,0,0,1,0,0,1,0,-1,2,0,0,2,0,-1,3,0,-2,4,0,-3,5,0,-4,6,0,0,3,0,0,3,0,0,4,0,0,4,0,0,5,0,0,5,0,0,6,0,0,6,0,6,1,17],[0,0,0,0,0,0,0,0,0],[1,1,3,4,1,3,4,1,-1],[0,0,1,2,3,1,2,3,5]],[[{"name":"combo2","rect":{"x":0,"y":0,"width":309,"height":74},"offset":{"x":0,"y":0},"originalSize":{"width":309,"height":74},"rotated":false,"capInsets":[0,0,0,0],"vertices":{"rawPosition":[-154.5,-37,0,154.5,-37,0,-154.5,37,0,154.5,37,0],"indexes":[0,1,2,2,1,3],"uv":[0,74,309,74,0,0,309,0],"nuv":[0,0,1,0,0,1,1,1],"minPos":{"x":-154.5,"y":-37,"z":0},"maxPos":{"x":154.5,"y":37,"z":0}},"packable":true,"pixelsToUnit":100,"pivot":{"x":0.5,"y":0.5},"meshType":0}],[1],0,[0],[2],[6]]]]
